geobootstrap/__init__.py
geobootstrap/kernel.py
geobootstrap/sample.py
geobootstrap/utils.py
geobootstrap-0.12.dist-info/METADATA
geobootstrap-0.12.dist-info/WHEEL
geobootstrap-0.12.dist-info/top_level.txt
geobootstrap-0.12.dist-info/RECORD
