Metadata-Version: 2.1
Name: geobootstrap
Version: 0.12
Summary: Python tools for geobootstrapping
Home-page: https://github.com/tastatham/geobootstrap
Author: Thomas Statham
Author-email: tastatham@gmail.com
License: MIT
Keywords: bootstrap,spatial
Requires-Dist: geopandas
Requires-Dist: scipy
